{
  "id": "2603.08574",
  "source_ids": {
    "arxiv": "2603.08574"
  },
  "title": "Scalable Neural Vocoder from Range-Null Space Decomposition",
  "authors": [
    "Andong Li",
    "Tong Lei",
    "Zhihang Sun",
    "Rilin Chen",
    "Xiaodong Li",
    "Dong Yu",
    "Chengshi Zheng"
  ],
  "authors_full": null,
  "organization": null,
  "venue": "arXiv",
  "venue_type": "preprint",
  "year": 2026,
  "month": 3,
  "published_date": "2026-03-09",
  "ingested_date": null,
  "url": "https://arxiv.org/abs/2603.08574",
  "pdf_url": "https://arxiv.org/pdf/2603.08574.pdf",
  "pdf_path": "raw/papers/2603.08574.pdf",
  "pdf_source": "arxiv",
  "abstract": "Although deep neural networks have facilitated significant progress of neural vocoders in recent years, they usually suffer from intrinsic challenges like opaque modeling, inflexible retraining under different input configurations, and parameter-performance trade-off. These inherent hurdles can heavily impede the development of this field. To resolve these problems, in this paper, we propose a novel neural vocoder in the time-frequency (T-F) domain. Specifically, we bridge the connection between the classical range-null decomposition (RND) theory and the vocoder task, where the reconstruction of the target spectrogram is formulated into the superimposition between range-space and null-space. The former aims to project the representation in the original mel-domain into the target linear-scale domain, and the latter can be instantiated via neural networks to further infill the spectral details. To fully leverage the spectrum prior, an elaborate dual-path framework is devised, where the spectrum is hierarchically encoded and decoded, and the cross- and narrow-band modules are leveraged for effectively modeling along sub-band and time dimensions. To enable inference under various configurations, we propose a simple yet effective strategy, which transforms the multi-condition adaption in the inference stage into the data augmentation in the training stage. Comprehensive experiments are conducted on various benchmarks. Quantitative and qualitative results show that while enjoying lightweight network structure and scalable inference paradigm, the proposed framework achieves state-ofthe-art performance among existing advanced methods. Code is available at https://github.com/Andong-Li-speech/RNDVoC.",
  "arxiv_comment": "30 pages, 30 figures, 21 tables, Extension journal",
  "task": [
    "TTS"
  ],
  "relevance_score": 0.88,
  "relevance_note": "Interpretable scalable neural vocoder using range-null space decomposition for flexible waveform synthesis",
  "status": "accepted",
  "fetched_date": "2026-05-19",
  "needs_manual_pdf": false,
  "is_duplicate": false,
  "canonical_id": null
}
